tusclient/__init__.py
tusclient/client.py
tusclient/exceptions.py
tusclient/request.py
tusclient/fingerprint/__init__.py
tusclient/fingerprint/fingerprint.py
tusclient/fingerprint/interface.py
tusclient/storage/__init__.py
tusclient/storage/filestorage.py
tusclient/storage/interface.py
tusclient/uploader/__init__.py
tusclient/uploader/baseuploader.py
tusclient/uploader/uploader.py
tator_tuspy-0.2.5.dist-info/AUTHORS
tator_tuspy-0.2.5.dist-info/LICENSE
tator_tuspy-0.2.5.dist-info/METADATA
tator_tuspy-0.2.5.dist-info/WHEEL
tator_tuspy-0.2.5.dist-info/top_level.txt
tator_tuspy-0.2.5.dist-info/RECORD
