Metadata-Version: 2.1
Name: tator-tuspy
Version: 0.2.5
Summary: Fork of a Python client for the tus resumable upload protocol ->  http://tus.io
Home-page: http://github.com/tus/tus-py-client/
Author: Ifedapo Olarewaju
Author-email: info@cvisionai.com
License: MIT
Platform: any
Classifier: Programming Language :: Python
Classifier: Natural Language :: English
Classifier: Environment :: Web Environment
Classifier: Intended Audience :: Developers
Classifier: Development Status :: 3 - Alpha
Classifier: License :: OSI Approved :: MIT License
Classifier: Operating System :: OS Independent
Classifier: Topic :: Software Development :: Libraries :: Python Modules
Classifier: Topic :: Internet :: File Transfer Protocol (FTP)
Classifier: Topic :: Communications :: File Sharing
Requires-Dist: aiohttp (>=3.6.2)
Requires-Dist: certifi (>=2018.1.18)
Requires-Dist: future (>=0.16.0)
Requires-Dist: requests (>=2.18.4)
Requires-Dist: six (>=1.11.0)
Requires-Dist: tinydb (>=3.5.0)
Provides-Extra: dev
Requires-Dist: Sphinx (==1.7.1) ; extra == 'dev'
Requires-Dist: sphinx-autobuild (==0.7.1) ; extra == 'dev'
Requires-Dist: tox (>=2.3.1) ; extra == 'dev'
Provides-Extra: test
Requires-Dist: aioresponses (>=0.6.2) ; extra == 'test'
Requires-Dist: coverage (>=4.2) ; extra == 'test'
Requires-Dist: pytest-cov (<2.6,>=2.3.1) ; extra == 'test'
Requires-Dist: pytest (>=3.0.3) ; extra == 'test'
Requires-Dist: responses (>=0.5.1) ; extra == 'test'
